docs/conf.py
floq/client/__init__.py
floq/client/api_client.py
floq/client/client.py
floq/client/containers.py
floq/client/errors.py
floq/client/jobs_queue.py
floq/client/schemas.py
floq/client/sse.py
floq/client/worker.py
floq/client/simulators/__init__.py
floq/client/simulators/cirq.py
floq/client/simulators/floq.py
samples/__init__.py
samples/jobs_queue.py
samples/pennylane.py
samples/simulate_expectation_values.py
samples/simulate_samples.py
samples/worker_manager.py
samples/worker_manager_async.py
scripts/__init__.py
scripts/cli.py
test/__init__.py
test/test_api_client.py
test/test_containers.py
test/test_jobs_queue.py
test/test_sse.py
test/test_worker.py
test/simulators/__init__.py
test/simulators/test_cirq.py
test/simulators/test_floq.py
floq_client-0.1.5.dist-info/LICENSE
floq_client-0.1.5.dist-info/METADATA
floq_client-0.1.5.dist-info/WHEEL
floq_client-0.1.5.dist-info/entry_points.txt
floq_client-0.1.5.dist-info/top_level.txt
floq_client-0.1.5.dist-info/RECORD
