Metadata-Version: 2.1
Name: floq-client
Version: 0.1.5
Summary: Floq Service client
Home-page: UNKNOWN
Author: Floq Team
Author-email: floq-devs@google.com
License: UNKNOWN
Platform: UNKNOWN
Classifier: Programming Language :: Python :: 3
Classifier: Operating System :: OS Independent
Requires-Python: >=3.7
Requires-Dist: cirq (==0.11.0)
Requires-Dist: dependency-injector (>=4.20.2)
Requires-Dist: marshmallow-dataclass (>=8.3.1)
Requires-Dist: marshmallow-enum (>=1.5.1)
Requires-Dist: marshmallow (>=3.10.0)
Requires-Dist: progressbar2 (>=3.53.1)
Requires-Dist: requests (>=2.24.0)
Requires-Dist: typeguard (>=2.12.1)
Provides-Extra: docs
Requires-Dist: sphinx-rtd-theme (>=0.5.2) ; extra == 'docs'
Requires-Dist: sphinx (>=4.1.2) ; extra == 'docs'
Requires-Dist: sphinxcontrib-napoleon (>=0.7) ; extra == 'docs'
